localpoly/__init__.py
localpoly/base.py
localpoly/utils/__init__.py
localpoly/utils/helpers.py
localpoly/utils/kernels.py
localpoly-0.1.4.dist-info/LICENSE
localpoly-0.1.4.dist-info/METADATA
localpoly-0.1.4.dist-info/WHEEL
localpoly-0.1.4.dist-info/top_level.txt
localpoly-0.1.4.dist-info/RECORD
