Metadata-Version: 2.1
Name: localpoly
Version: 0.1.4
Summary: Performs Local Polynomial Regression.
Home-page: https://github.com/franwe/localpoly
Author: franwe
Author-email: franziska.wehrmann@gmail.com
License: MIT
Project-URL: Documentation, https://localpoly.readthedocs.io/en/latest/
Project-URL: Code, https://github.com/franwe/localpoly
Platform: UNKNOWN
Requires-Python: >=3
Requires-Dist: numpy
Requires-Dist: pandas
Requires-Dist: scipy
